django_powerbank/__init__.py
django_powerbank/app_settings.py
django_powerbank/apps.py
django_powerbank/core/__init__.py
django_powerbank/core/validators.py
django_powerbank/db/__init__.py
django_powerbank/db/models/__init__.py
django_powerbank/db/models/base.py
django_powerbank/db/models/query.py
django_powerbank/db/models/fields/__init__.py
django_powerbank/db/models/fields/pl.py
django_powerbank/forms/__init__.py
django_powerbank/forms/fields.py
django_powerbank/forms/widgets.py
django_powerbank/forms/generic/edit.py
django_powerbank/locale/babel.cfg
django_powerbank/locale/django.pot
django_powerbank/locale/pl/LC_MESSAGES/django.po
django_powerbank/templates/django_powerbank/forms/widgets/selectize/script.html
django_powerbank/templates/django_powerbank/forms/widgets/selectize/select.html
django_powerbank/templates/django_powerbank/forms/widgets/selectize/tags.html
django_powerbank/testing/__init__.py
django_powerbank/testing/base.py
django_powerbank/testing/factories.py
django_powerbank/testing/utils.py
django_powerbank/views/__init__.py
django_powerbank/views/auth.py
django_powerbank/views/generic.py
django_powerbank/views/mixins.py
django_powerbank-0.4.2.dist-info/AUTHORS.rst
django_powerbank-0.4.2.dist-info/LICENSE
django_powerbank-0.4.2.dist-info/METADATA
django_powerbank-0.4.2.dist-info/WHEEL
django_powerbank-0.4.2.dist-info/entry_points.txt
django_powerbank-0.4.2.dist-info/top_level.txt
django_powerbank-0.4.2.dist-info/RECORD
