Metadata-Version: 2.1
Name: django-powerbank
Version: 0.4.2
Summary: Extra power for included batteries
Home-page: https://github.com/wooyek/django-powerbank
Author: Janusz Skonieczny
Author-email: js+pypi@bravelabs.pl
License: MIT license
Keywords: django-powerbank
Platform: UNKNOWN
Classifier: Development Status :: 3 - Alpha
Classifier: Framework :: Django :: 1.10
Classifier: Intended Audience :: Developers
Classifier: License :: OSI Approved :: MIT License
Classifier: Natural Language :: English
Classifier: Programming Language :: Python :: 2.7
Classifier: Programming Language :: Python :: 3.5
Requires-Python: >=2.7
Requires-Dist: django-localflavor
Requires-Dist: markdown
Requires-Dist: django (>=1.11)
Requires-Dist: enum34 ; python_version < "3.4"
Provides-Extra: factories
Requires-Dist: factory-boy ; extra == 'factories'
